{
    "actionOnStepFail": null, 
    "concurrency": 1, 
    "enabled": true, 
    "externalUuid4": "304d0067-e6f1-4c67-9216-34fe0a4dc302", 
    "isBlueprint": true, 
    "key": "peekv3lindeployrelease", 
    "links": [
        {
            "order": 20, 
            "stepKey": "peekv3linpdrecleaninstallfiles"
        }, 
        {
            "order": 70, 
            "stepKey": "peekv3pullreleasefromnexus"
        }, 
        {
            "order": 120, 
            "stepKey": "peekv3extractrelease"
        }, 
        {
            "order": 170, 
            "stepKey": "peekv3linpdrestoppeek"
        }, 
        {
            "order": 220, 
            "stepKey": "peekv3linpdredeleteoldreleases"
        }, 
        {
            "order": 270, 
            "stepKey": "peekv3linpdredeleteoldlogs"
        }, 
        {
            "order": 320, 
            "stepKey": "peekv3linpdreinstallrelease"
        }, 
        {
            "order": 370, 
            "stepKey": "peekv3linpdrecheckpackageversions"
        }, 
        {
            "order": 420, 
            "stepKey": "peekv3linpdrepatchpeekutilscripts"
        }, 
        {
            "order": 470, 
            "stepKey": "peekv3linpdreinstallsystemdandrestart"
        }, 
        {
            "order": 520, 
            "stepKey": "peekv3linpdrecleaninstallfiles"
        }, 
        {
            "order": 570, 
            "stepKey": "peekv3linpdrelistpackages"
        }
    ], 
    "name": "Peek v3 LIN Deploy Release ", 
    "type": "com.servertribe.attune.tuples.StepGroupTuple"
}